argument_checks/__init__.py
argument_checks/decorators.py
argument_checks/verifications.py
argument_checks-0.1.1.dist-info/LICENSE
argument_checks-0.1.1.dist-info/WHEEL
argument_checks-0.1.1.dist-info/METADATA
argument_checks-0.1.1.dist-info/RECORD
